[{"name": "Pet Detective", "year": 1994, "printQuality": "1080p", "fileName": "Ace.Ventura_.Pet.Detective.1994.1080p.BluRay.x264.YIFY.mp4","seriesName": "Ace Ventura","isHindi": false}, {"name": "When Nature Calls", "year": 1995, "printQuality": "1080p", "fileName": "Ace.Ventura_.When.Nature.Calls.1995.1080p.BluRay.x264.YIFY.mp4","seriesName": "Ace Ventura","isHindi": false}, {"name": "Hot Tub Time Machine", "year": 2010, "printQuality": "1080p", "fileName": "Hot.Tub.Time.Machine.2010.1080p.BrRip.x264.BOKUTOX.YIFY.mp4","seriesName": "Hot Tub Time Machine","isHindi": false}, {"name": "Hot Tub Time Machine 2", "year": 2015, "printQuality": "1080p", "fileName": "Hot.Tub.Time.Machine.2.2015.1080p.BluRay.x264.YIFY.mp4","seriesName": "Hot Tub Time Machine","isHindi": false}, {"name": "Bean", "year": 1997, "printQuality": "", "fileName": "Mr. Bean-1.mkv","seriesName": "Mr. Bean","isHindi": false}, {"name": "Mr Beans Holiday", "year": 2007, "printQuality": "720p", "fileName": "Mr.Beans.Holiday.2007.BluRay.720p.x264.AC3-WOFEI.mkv","seriesName": "Mr. Bean","isHindi": false}, {"name": "Battle of the Smithsonian", "year": 2009, "printQuality": "720p", "fileName": "Night.at.the.Museum.2.(2009).720p.BrRip.Dual.audio..mkv","seriesName": "Night at the Museum","isHindi": false}, {"name": "Night at the Museum", "year": 2006, "printQuality": "1080p", "fileName": "Night.at.the.Museum.2006.1080p.BrRip.x264.YIFY.mp4","seriesName": "Night at the Museum","isHindi": false}, {"name": "Secret of the Tomb", "year": 2014, "printQuality": "720p", "fileName": "Night.at.the.Museum.Secret.of.the.Tomb.2014.720p.BluRay.x264.YIFY.mp4","seriesName": "Night at the Museum","isHindi": false}, {"name": "Rush Hour 1", "year": 1998, "printQuality": "720p", "fileName": "Rush.Hour.1(1998).720p.BrRip.x264.Dual.audio.(Eng-Hin).{mjRocks91}.mkv","seriesName": "Rush Hour","isHindi": false}, {"name": "Rush Hour 2", "year": 2001, "printQuality": "720p", "fileName": "Rush Hour 2 2001 BRRip 720p h264.mkv","seriesName": "Rush Hour","isHindi": false}, {"name": "Ted", "year": 2012, "printQuality": "720p", "fileName": "Ted.2012.BluRay.720p.x264.YIFY.mp4","seriesName": "Ted","isHindi": false}, {"name": "Ted 2", "year": 2015, "printQuality": "1080p", "fileName": "Ted 2 2015 UNCENSORED 1080p HC HDRip x264 AAC-JYK.mkv","seriesName": "Ted","isHindi": false}, {"name": "The Dictator", "year": 2012, "printQuality": "720p", "fileName": "The Dictator (2012) UNRATED 720p BRRip x264[Dual-Audio][Eng-Hindi 6CH] By Mafiaking [Team EXD].mkv","seriesName": "","isHindi": true}, {"name": "The Dictator", "year": 2012, "printQuality": "", "fileName": "The.Dictator.2012.mkv","seriesName": "","isHindi": false}, {"name": "The Hangover", "year": 2009, "printQuality": "DVD", "fileName": "Hangover1.Dual.300MB DVD [Hindi].mkv","seriesName": "The Hangover","isHindi": true}, {"name": "The Hangover", "year": 2009, "printQuality": "720p", "fileName": "The.Hangover.2009.UNRATED.720p.BrRip.x264.YIFY.mp4","seriesName": "The Hangover","isHindi": false}, {"name": "The Hangover Part II", "year": 2011, "printQuality": "720p", "fileName": "The.Hangover.Part.II.2011.720p.BrRip.x264.YIFY.mp4","seriesName": "The Hangover","isHindi": false}, {"name": "The Hangover Part III", "year": 2013, "printQuality": "720p", "fileName": "The Hangover Part III (2013)720p BrRip Dual Audio(Hindi-English)By Lokioddin(PimpRG).mkv","seriesName": "The Hangover","isHindi": true}]